{
  "status": "success",
  "exchanges_scanned": [
    "binance",
    "kraken",
    "kucoin",
    "gateio",
    "coinbase"
  ],
  "profit_threshold_pct": 0.2,
  "opportunities_found": 81,
  "data": [
    {
      "symbol": "HOLD/USDT",
      "buy_on": "gateio",
      "buy_price": 8.299e-06,
      "sell_on": "kucoin",
      "sell_price": 0.8301,
      "profit_pct": 10002309.9289
    },
    {
      "symbol": "ZERO/USDT",
      "buy_on": "kucoin",
      "buy_price": 1.002e-05,
      "sell_on": "gateio",
      "sell_price": 0.07727,
      "profit_pct": 771057.6846
    },
    {
      "symbol": "ACE/USDT",
      "buy_on": "kucoin",
      "buy_price": 5.03e-05,
      "sell_on": "gateio",
      "sell_price": 0.2243,
      "profit_pct": 445824.4533
    },
    {
      "symbol": "ATOM3L/USDT",
      "buy_on": "kucoin",
      "buy_price": 0.00018073,
      "sell_on": "gateio",
      "sell_price": 0.4703,
      "profit_pct": 260122.4313
    },
    {
      "symbol": "BTC3L/USDT",
      "buy_on": "kucoin",
      "buy_price": 0.004672,
      "sell_on": "gateio",
      "sell_price": 5.7001,
      "profit_pct": 121905.5651
    },
    {
      "symbol": "DOGE3S/USDT",
      "buy_on": "gateio",
      "buy_price": 0.003964,
      "sell_on": "kucoin",
      "sell_price": 2.3642,
      "profit_pct": 59541.776
    },
    {
      "symbol": "BTC3S/USDT",
      "buy_on": "kucoin",
      "buy_price": 0.00012787,
      "sell_on": "gateio",
      "sell_price": 0.0654,
      "profit_pct": 51045.6948
    },
    {
      "symbol": "DOGE3L/USDT",
      "buy_on": "gateio",
      "buy_price": 0.002685,
      "sell_on": "kucoin",
      "sell_price": 0.8493,
      "profit_pct": 31531.2849
    },
    {
      "symbol": "BNB3S/USDT",
      "buy_on": "gateio",
      "buy_price": 0.007094,
      "sell_on": "kucoin",
      "sell_price": 1.8061,
      "profit_pct": 25359.5433
    },
    {
      "symbol": "XRP3S/USDT",
      "buy_on": "kucoin",
      "buy_price": 0.003943,
      "sell_on": "gateio",
      "sell_price": 0.45155,
      "profit_pct": 11351.9401
    },
    {
      "symbol": "ETH3S/USDT",
      "buy_on": "kucoin",
      "buy_price": 0.006066,
      "sell_on": "gateio",
      "sell_price": 0.5114,
      "profit_pct": 8330.5968
    },
    {
      "symbol": "SOL3L/USDT",
      "buy_on": "kucoin",
      "buy_price": 0.05230814,
      "sell_on": "gateio",
      "sell_price": 1.745,
      "profit_pct": 3236.0009
    },
    {
      "symbol": "BROCCOLI/USDT",
      "buy_on": "kucoin",
      "buy_price": 0.002373,
      "sell_on": "gateio",
      "sell_price": 0.01442,
      "profit_pct": 507.6696
    },
    {
      "symbol": "ATOM3S/USDT",
      "buy_on": "kucoin",
      "buy_price": 0.232,
      "sell_on": "gateio",
      "sell_price": 0.7831,
      "profit_pct": 237.5431
    },
    {
      "symbol": "ETH3L/USDT",
      "buy_on": "gateio",
      "buy_price": 0.7696,
      "sell_on": "kucoin",
      "sell_price": 2.5588,
      "profit_pct": 232.4844
    },
    {
      "symbol": "XYRO/USDT",
      "buy_on": "gateio",
      "buy_price": 0.0004629,
      "sell_on": "kucoin",
      "sell_price": 0.001318,
      "profit_pct": 184.7267
    },
    {
      "symbol": "QI/USDT",
      "buy_on": "gateio",
      "buy_price": 0.0014713,
      "sell_on": "kucoin",
      "sell_price": 0.003793,
      "profit_pct": 157.7992
    },
    {
      "symbol": "BNB3L/USDT",
      "buy_on": "kucoin",
      "buy_price": 0.1395,
      "sell_on": "gateio",
      "sell_price": 0.2855,
      "profit_pct": 104.6595
    },
    {
      "symbol": "STAGE/USDT",
      "buy_on": "gateio",
      "buy_price": 2.19e-05,
      "sell_on": "kucoin",
      "sell_price": 4.245e-05,
      "profit_pct": 93.8356
    },
    {
      "symbol": "RWA/USDT",
      "buy_on": "gateio",
      "buy_price": 0.003404,
      "sell_on": "kucoin",
      "sell_price": 0.006191,
      "profit_pct": 81.8743
    },
    {
      "symbol": "LTC3S/USDT",
      "buy_on": "kucoin",
      "buy_price": 0.1649,
      "sell_on": "gateio",
      "sell_price": 0.29007,
      "profit_pct": 75.9066
    },
    {
      "symbol": "NUMI/USDT",
      "buy_on": "gateio",
      "buy_price": 0.07235,
      "sell_on": "kucoin",
      "sell_price": 0.12576,
      "profit_pct": 73.8217
    },
    {
      "symbol": "SLN/USDT",
      "buy_on": "gateio",
      "buy_price": 0.004733,
      "sell_on": "kucoin",
      "sell_price": 0.00801,
      "profit_pct": 69.2373
    },
    {
      "symbol": "LTC3L/USDT",
      "buy_on": "gateio",
      "buy_price": 0.02457,
      "sell_on": "kucoin",
      "sell_price": 0.038616,
      "profit_pct": 57.1673
    },
    {
      "symbol": "GST/USDT",
      "buy_on": "gateio",
      "buy_price": 0.001651,
      "sell_on": "kucoin",
      "sell_price": 0.002591,
      "profit_pct": 56.9352
    },
    {
      "symbol": "BRAWL/USDT",
      "buy_on": "gateio",
      "buy_price": 1.293e-05,
      "sell_on": "kucoin",
      "sell_price": 1.99e-05,
      "profit_pct": 53.9056
    },
    {
      "symbol": "DIN/USDT",
      "buy_on": "kucoin",
      "buy_price": 0.057,
      "sell_on": "gateio",
      "sell_price": 0.08685,
      "profit_pct": 52.3684
    },
    {
      "symbol": "NGL/USDT",
      "buy_on": "gateio",
      "buy_price": 0.003199,
      "sell_on": "kucoin",
      "sell_price": 0.004791,
      "profit_pct": 49.7656
    },
    {
      "symbol": "CLV/USDT",
      "buy_on": "gateio",
      "buy_price": 0.00432,
      "sell_on": "kucoin",
      "sell_price": 0.00646,
      "profit_pct": 49.537
    },
    {
      "symbol": "MXC/USDT",
      "buy_on": "gateio",
      "buy_price": 3e-05,
      "sell_on": "kucoin",
      "sell_price": 4.4e-05,
      "profit_pct": 46.6667
    },
    {
      "symbol": "SOL3S/USDT",
      "buy_on": "kucoin",
      "buy_price": 0.4107,
      "sell_on": "gateio",
      "sell_price": 0.59365,
      "profit_pct": 44.5459
    },
    {
      "symbol": "PIP/USDT",
      "buy_on": "gateio",
      "buy_price": 0.0006554,
      "sell_on": "kucoin",
      "sell_price": 0.0008963,
      "profit_pct": 36.7562
    },
    {
      "symbol": "AEG/USDT",
      "buy_on": "gateio",
      "buy_price": 0.0001965,
      "sell_on": "kucoin",
      "sell_price": 0.0002302,
      "profit_pct": 17.1501
    },
    {
      "symbol": "OMNIA/USDT",
      "buy_on": "gateio",
      "buy_price": 0.004006,
      "sell_on": "kucoin",
      "sell_price": 0.004545,
      "profit_pct": 13.4548
    },
    {
      "symbol": "VRA/USDT",
      "buy_on": "gateio",
      "buy_price": 0.0003622,
      "sell_on": "kucoin",
      "sell_price": 0.0003962,
      "profit_pct": 9.3871
    },
    {
      "symbol": "FEAR/USDT",
      "buy_on": "gateio",
      "buy_price": 0.00258,
      "sell_on": "kucoin",
      "sell_price": 0.0028,
      "profit_pct": 8.5271
    },
    {
      "symbol": "GODL/USDT",
      "buy_on": "gateio",
      "buy_price": 0.0001497,
      "sell_on": "kucoin",
      "sell_price": 0.0001569,
      "profit_pct": 4.8096
    },
    {
      "symbol": "PBX/USDT",
      "buy_on": "gateio",
      "buy_price": 4.88e-05,
      "sell_on": "kucoin",
      "sell_price": 5e-05,
      "profit_pct": 2.459
    },
    {
      "symbol": "MTV/USDT",
      "buy_on": "gateio",
      "buy_price": 0.0003269,
      "sell_on": "kucoin",
      "sell_price": 0.0003349,
      "profit_pct": 2.4472
    },
    {
      "symbol": "ELF/USDT",
      "buy_on": "kucoin",
      "buy_price": 0.089,
      "sell_on": "gateio",
      "sell_price": 0.0911,
      "profit_pct": 2.3596
    },
    {
      "symbol": "LOOKS/USDT",
      "buy_on": "gateio",
      "buy_price": 0.001955,
      "sell_on": "kucoin",
      "sell_price": 0.002,
      "profit_pct": 2.3018
    },
    {
      "symbol": "MYRIA/USDT",
      "buy_on": "gateio",
      "buy_price": 0.0001212,
      "sell_on": "kucoin",
      "sell_price": 0.0001239,
      "profit_pct": 2.2277
    },
    {
      "symbol": "PFVS/USDT",
      "buy_on": "gateio",
      "buy_price": 0.002147,
      "sell_on": "kucoin",
      "sell_price": 0.002176,
      "profit_pct": 1.3507
    },
    {
      "symbol": "USTC/USDT",
      "buy_on": "kraken",
      "buy_price": 0.00605,
      "sell_on": "kucoin",
      "sell_price": 0.00613,
      "profit_pct": 1.3223
    },
    {
      "symbol": "XRP3L/USDT",
      "buy_on": "kucoin",
      "buy_price": 0.8471,
      "sell_on": "gateio",
      "sell_price": 0.8581,
      "profit_pct": 1.2985
    },
    {
      "symbol": "XEM/USDT",
      "buy_on": "kucoin",
      "buy_price": 0.001591,
      "sell_on": "gateio",
      "sell_price": 0.0016088,
      "profit_pct": 1.1188
    },
    {
      "symbol": "TUSD/USDT",
      "buy_on": "kucoin",
      "buy_price": 0.9879,
      "sell_on": "gateio",
      "sell_price": 0.9981,
      "profit_pct": 1.0325
    },
    {
      "symbol": "DEFI/USDT",
      "buy_on": "kucoin",
      "buy_price": 0.000807,
      "sell_on": "gateio",
      "sell_price": 0.0008153,
      "profit_pct": 1.0285
    },
    {
      "symbol": "ARCA/USDT",
      "buy_on": "gateio",
      "buy_price": 0.0094,
      "sell_on": "kucoin",
      "sell_price": 0.00948,
      "profit_pct": 0.8511
    },
    {
      "symbol": "UOS/USDT",
      "buy_on": "gateio",
      "buy_price": 0.010356,
      "sell_on": "kucoin",
      "sell_price": 0.01044,
      "profit_pct": 0.8111
    },
    {
      "symbol": "CHIRP/USDT",
      "buy_on": "gateio",
      "buy_price": 0.02486,
      "sell_on": "kucoin",
      "sell_price": 0.02505,
      "profit_pct": 0.7643
    },
    {
      "symbol": "MILK/USDT",
      "buy_on": "gateio",
      "buy_price": 0.01227,
      "sell_on": "kucoin",
      "sell_price": 0.01236,
      "profit_pct": 0.7335
    },
    {
      "symbol": "ITHACA/USDT",
      "buy_on": "gateio",
      "buy_price": 0.005143,
      "sell_on": "kucoin",
      "sell_price": 0.0051805,
      "profit_pct": 0.7291
    },
    {
      "symbol": "MAN/USDT",
      "buy_on": "gateio",
      "buy_price": 0.003577,
      "sell_on": "kucoin",
      "sell_price": 0.003601,
      "profit_pct": 0.671
    },
    {
      "symbol": "BIFIF/USDT",
      "buy_on": "gateio",
      "buy_price": 0.0008345,
      "sell_on": "kucoin",
      "sell_price": 0.00084,
      "profit_pct": 0.6591
    },
    {
      "symbol": "VOLT/USDT",
      "buy_on": "gateio",
      "buy_price": 7.939e-08,
      "sell_on": "kucoin",
      "sell_price": 7.99e-08,
      "profit_pct": 0.6424
    },
    {
      "symbol": "ROOT/USDT",
      "buy_on": "gateio",
      "buy_price": 0.0002514,
      "sell_on": "kucoin",
      "sell_price": 0.000253,
      "profit_pct": 0.6364
    },
    {
      "symbol": "VANRY/USDT",
      "buy_on": "gateio",
      "buy_price": 0.010017,
      "sell_on": "kucoin",
      "sell_price": 0.01008,
      "profit_pct": 0.6289
    },
    {
      "symbol": "MTRG/USDT",
      "buy_on": "gateio",
      "buy_price": 0.03515,
      "sell_on": "kucoin",
      "sell_price": 0.03537,
      "profit_pct": 0.6259
    },
    {
      "symbol": "HIFI/USDT",
      "buy_on": "gateio",
      "buy_price": 0.03159,
      "sell_on": "kucoin",
      "sell_price": 0.03178,
      "profit_pct": 0.6015
    },
    {
      "symbol": "ARTFI/USDT",
      "buy_on": "kucoin",
      "buy_price": 0.0017,
      "sell_on": "gateio",
      "sell_price": 0.00171,
      "profit_pct": 0.5882
    },
    {
      "symbol": "FOMO/USDT",
      "buy_on": "gateio",
      "buy_price": 9.624e-06,
      "sell_on": "kucoin",
      "sell_price": 9.68e-06,
      "profit_pct": 0.5819
    },
    {
      "symbol": "BOSON/USDT",
      "buy_on": "gateio",
      "buy_price": 0.04227,
      "sell_on": "kucoin",
      "sell_price": 0.0425,
      "profit_pct": 0.5441
    },
    {
      "symbol": "EGP/USDT",
      "buy_on": "kucoin",
      "buy_price": 0.2898,
      "sell_on": "gateio",
      "sell_price": 0.2913,
      "profit_pct": 0.5176
    },
    {
      "symbol": "VAIOT/USDT",
      "buy_on": "kucoin",
      "buy_price": 0.01065,
      "sell_on": "gateio",
      "sell_price": 0.0107,
      "profit_pct": 0.4695
    },
    {
      "symbol": "BCUT/USDT",
      "buy_on": "gateio",
      "buy_price": 0.006225,
      "sell_on": "kucoin",
      "sell_price": 0.006251,
      "profit_pct": 0.4177
    },
    {
      "symbol": "CWS/USDT",
      "buy_on": "kucoin",
      "buy_price": 0.0762,
      "sell_on": "gateio",
      "sell_price": 0.07651,
      "profit_pct": 0.4068
    },
    {
      "symbol": "DCK/USDT",
      "buy_on": "kucoin",
      "buy_price": 0.002565,
      "sell_on": "gateio",
      "sell_price": 0.002575,
      "profit_pct": 0.3899
    },
    {
      "symbol": "XCV/USDT",
      "buy_on": "kucoin",
      "buy_price": 0.000415,
      "sell_on": "gateio",
      "sell_price": 0.0004166,
      "profit_pct": 0.3855
    },
    {
      "symbol": "ELP/USDT",
      "buy_on": "kucoin",
      "buy_price": 0.004211,
      "sell_on": "gateio",
      "sell_price": 0.004227,
      "profit_pct": 0.38
    },
    {
      "symbol": "PHIL/USDT",
      "buy_on": "gateio",
      "buy_price": 0.0007203,
      "sell_on": "kucoin",
      "sell_price": 0.000723,
      "profit_pct": 0.3748
    },
    {
      "symbol": "REVU/USDT",
      "buy_on": "gateio",
      "buy_price": 0.002964,
      "sell_on": "kucoin",
      "sell_price": 0.002975,
      "profit_pct": 0.3711
    },
    {
      "symbol": "OAS/USDT",
      "buy_on": "kucoin",
      "buy_price": 0.002159,
      "sell_on": "gateio",
      "sell_price": 0.002167,
      "profit_pct": 0.3705
    },
    {
      "symbol": "NAM/USDT",
      "buy_on": "kucoin",
      "buy_price": 0.00722,
      "sell_on": "gateio",
      "sell_price": 0.007245,
      "profit_pct": 0.3463
    },
    {
      "symbol": "PRAI/USDT",
      "buy_on": "gateio",
      "buy_price": 0.008422,
      "sell_on": "kucoin",
      "sell_price": 0.00845,
      "profit_pct": 0.3325
    },
    {
      "symbol": "SQD/USDT",
      "buy_on": "kucoin",
      "buy_price": 0.05445,
      "sell_on": "gateio",
      "sell_price": 0.0546,
      "profit_pct": 0.2755
    },
    {
      "symbol": "PLUME/USDT",
      "buy_on": "gateio",
      "buy_price": 0.02109,
      "sell_on": "kucoin",
      "sell_price": 0.02114,
      "profit_pct": 0.2371
    },
    {
      "symbol": "USDT/EUR",
      "buy_on": "kraken",
      "buy_price": 0.8583,
      "sell_on": "kucoin",
      "sell_price": 0.8603,
      "profit_pct": 0.233
    },
    {
      "symbol": "RESOLV/USDT",
      "buy_on": "gateio",
      "buy_price": 0.07413,
      "sell_on": "kucoin",
      "sell_price": 0.0743,
      "profit_pct": 0.2293
    },
    {
      "symbol": "KIP/USDT",
      "buy_on": "gateio",
      "buy_price": 0.0001789,
      "sell_on": "kucoin",
      "sell_price": 0.0001793,
      "profit_pct": 0.2236
    },
    {
      "symbol": "WEMIX/USDT",
      "buy_on": "kucoin",
      "buy_price": 0.4492,
      "sell_on": "gateio",
      "sell_price": 0.4501,
      "profit_pct": 0.2004
    }
  ]
}