{
  "status": "success",
  "exchanges_scanned": [
    "binance",
    "kraken",
    "kucoin",
    "gateio",
    "coinbase"
  ],
  "profit_threshold_pct": 0.2,
  "opportunities_found": 121,
  "data": [
    {
      "symbol": "HOLD/USDT",
      "buy_on": "gateio",
      "buy_price": 1.3074e-05,
      "sell_on": "kucoin",
      "sell_price": 1.0331,
      "profit_pct": 7901842.7872
    },
    {
      "symbol": "POP/USDT",
      "buy_on": "gateio",
      "buy_price": 4.869e-08,
      "sell_on": "kucoin",
      "sell_price": 0.001146,
      "profit_pct": 2353566.0505
    },
    {
      "symbol": "SUI3L/USDT",
      "buy_on": "kucoin",
      "buy_price": 5.339e-05,
      "sell_on": "gateio",
      "sell_price": 1.08254,
      "profit_pct": 2027508.1663
    },
    {
      "symbol": "ZERO/USDT",
      "buy_on": "kucoin",
      "buy_price": 8.38e-06,
      "sell_on": "gateio",
      "sell_price": 0.08818,
      "profit_pct": 1052167.3031
    },
    {
      "symbol": "ACE/USDT",
      "buy_on": "kucoin",
      "buy_price": 4.96e-05,
      "sell_on": "gateio",
      "sell_price": 0.2613,
      "profit_pct": 526714.5161
    },
    {
      "symbol": "UNI3L/USDT",
      "buy_on": "kucoin",
      "buy_price": 0.00016345,
      "sell_on": "gateio",
      "sell_price": 0.81078,
      "profit_pct": 495941.6029
    },
    {
      "symbol": "ATOM3L/USDT",
      "buy_on": "kucoin",
      "buy_price": 0.00030164,
      "sell_on": "gateio",
      "sell_price": 0.92115,
      "profit_pct": 305280.5861
    },
    {
      "symbol": "LINK3S/USDT",
      "buy_on": "kucoin",
      "buy_price": 0.00025353,
      "sell_on": "gateio",
      "sell_price": 0.5871,
      "profit_pct": 231470.2284
    },
    {
      "symbol": "TAP/USDT",
      "buy_on": "gateio",
      "buy_price": 0.00012948,
      "sell_on": "kucoin",
      "sell_price": 0.23,
      "profit_pct": 177533.6114
    },
    {
      "symbol": "SUSHI3L/USDT",
      "buy_on": "kucoin",
      "buy_price": 4.392e-05,
      "sell_on": "gateio",
      "sell_price": 0.05868,
      "profit_pct": 133506.5574
    },
    {
      "symbol": "BTC3L/USDT",
      "buy_on": "kucoin",
      "buy_price": 0.006714,
      "sell_on": "gateio",
      "sell_price": 8.4638,
      "profit_pct": 125961.9601
    },
    {
      "symbol": "DOGE3S/USDT",
      "buy_on": "gateio",
      "buy_price": 0.004052,
      "sell_on": "kucoin",
      "sell_price": 2.2845,
      "profit_pct": 56279.5656
    },
    {
      "symbol": "BTC3S/USDT",
      "buy_on": "kucoin",
      "buy_price": 0.0001081,
      "sell_on": "gateio",
      "sell_price": 0.05942,
      "profit_pct": 54867.6226
    },
    {
      "symbol": "DOGE3L/USDT",
      "buy_on": "gateio",
      "buy_price": 0.004452,
      "sell_on": "kucoin",
      "sell_price": 1.3575,
      "profit_pct": 30391.9137
    },
    {
      "symbol": "NEAR3S/USDT",
      "buy_on": "gateio",
      "buy_price": 0.01387,
      "sell_on": "kucoin",
      "sell_price": 4.1001,
      "profit_pct": 29460.9229
    },
    {
      "symbol": "BNB3S/USDT",
      "buy_on": "gateio",
      "buy_price": 0.007003,
      "sell_on": "kucoin",
      "sell_price": 1.6355,
      "profit_pct": 23254.2767
    },
    {
      "symbol": "ADA3L/USDT",
      "buy_on": "kucoin",
      "buy_price": 3.36e-05,
      "sell_on": "gateio",
      "sell_price": 0.006274,
      "profit_pct": 18572.619
    },
    {
      "symbol": "BCH3S/USDT",
      "buy_on": "kucoin",
      "buy_price": 0.003268,
      "sell_on": "gateio",
      "sell_price": 0.5602,
      "profit_pct": 17041.9829
    },
    {
      "symbol": "XRP3S/USDT",
      "buy_on": "kucoin",
      "buy_price": 0.004893,
      "sell_on": "gateio",
      "sell_price": 0.58662,
      "profit_pct": 11888.9638
    },
    {
      "symbol": "ETH3S/USDT",
      "buy_on": "kucoin",
      "buy_price": 0.005572,
      "sell_on": "gateio",
      "sell_price": 0.495,
      "profit_pct": 8783.7042
    },
    {
      "symbol": "LINK3L/USDT",
      "buy_on": "kucoin",
      "buy_price": 0.021043,
      "sell_on": "gateio",
      "sell_price": 1.067,
      "profit_pct": 4970.5698
    },
    {
      "symbol": "SOL3L/USDT",
      "buy_on": "kucoin",
      "buy_price": 0.08234297,
      "sell_on": "gateio",
      "sell_price": 2.846,
      "profit_pct": 3356.2756
    },
    {
      "symbol": "BCH3L/USDT",
      "buy_on": "gateio",
      "buy_price": 0.03702,
      "sell_on": "kucoin",
      "sell_price": 0.620093,
      "profit_pct": 1575.0216
    },
    {
      "symbol": "AVAX3L/USDT",
      "buy_on": "kucoin",
      "buy_price": 0.00050046,
      "sell_on": "gateio",
      "sell_price": 0.005446,
      "profit_pct": 988.1989
    },
    {
      "symbol": "BROCCOLI/USDT",
      "buy_on": "kucoin",
      "buy_price": 0.002212,
      "sell_on": "gateio",
      "sell_price": 0.01781,
      "profit_pct": 705.1537
    },
    {
      "symbol": "AAVE3L/USDT",
      "buy_on": "kucoin",
      "buy_price": 0.00469431,
      "sell_on": "gateio",
      "sell_price": 0.03315,
      "profit_pct": 606.1741
    },
    {
      "symbol": "ATOM3S/USDT",
      "buy_on": "kucoin",
      "buy_price": 0.2346,
      "sell_on": "gateio",
      "sell_price": 0.9295,
      "profit_pct": 296.2063
    },
    {
      "symbol": "ETH3L/USDT",
      "buy_on": "gateio",
      "buy_price": 1.1793,
      "sell_on": "kucoin",
      "sell_price": 3.788,
      "profit_pct": 221.2075
    },
    {
      "symbol": "QI/USDT",
      "buy_on": "gateio",
      "buy_price": 0.001607,
      "sell_on": "kucoin",
      "sell_price": 0.004408,
      "profit_pct": 174.2999
    },
    {
      "symbol": "UNI3S/USDT",
      "buy_on": "kucoin",
      "buy_price": 0.0922,
      "sell_on": "gateio",
      "sell_price": 0.20851,
      "profit_pct": 126.1497
    },
    {
      "symbol": "LTC3S/USDT",
      "buy_on": "kucoin",
      "buy_price": 0.2006,
      "sell_on": "gateio",
      "sell_price": 0.44962,
      "profit_pct": 124.1376
    },
    {
      "symbol": "BNB3L/USDT",
      "buy_on": "kucoin",
      "buy_price": 0.1895,
      "sell_on": "gateio",
      "sell_price": 0.4067,
      "profit_pct": 114.6174
    },
    {
      "symbol": "SUSHI3S/USDT",
      "buy_on": "gateio",
      "buy_price": 0.02785,
      "sell_on": "kucoin",
      "sell_price": 0.058071,
      "profit_pct": 108.5135
    },
    {
      "symbol": "APE3S/USDT",
      "buy_on": "kucoin",
      "buy_price": 0.006538,
      "sell_on": "gateio",
      "sell_price": 0.013291,
      "profit_pct": 103.2885
    },
    {
      "symbol": "AVAX3S/USDT",
      "buy_on": "kucoin",
      "buy_price": 0.1405,
      "sell_on": "gateio",
      "sell_price": 0.26474,
      "profit_pct": 88.427
    },
    {
      "symbol": "SUI3S/USDT",
      "buy_on": "gateio",
      "buy_price": 0.08446,
      "sell_on": "kucoin",
      "sell_price": 0.1508,
      "profit_pct": 78.5461
    },
    {
      "symbol": "SOL3S/USDT",
      "buy_on": "kucoin",
      "buy_price": 0.3906,
      "sell_on": "gateio",
      "sell_price": 0.59316,
      "profit_pct": 51.8587
    },
    {
      "symbol": "LTC3L/USDT",
      "buy_on": "gateio",
      "buy_price": 0.03582,
      "sell_on": "kucoin",
      "sell_price": 0.0542,
      "profit_pct": 51.3121
    },
    {
      "symbol": "MAK/USDT",
      "buy_on": "gateio",
      "buy_price": 0.001787,
      "sell_on": "kucoin",
      "sell_price": 0.002589,
      "profit_pct": 44.8797
    },
    {
      "symbol": "APE3L/USDT",
      "buy_on": "gateio",
      "buy_price": 1.98405,
      "sell_on": "kucoin",
      "sell_price": 2.8636,
      "profit_pct": 44.331
    },
    {
      "symbol": "GST/USDT",
      "buy_on": "gateio",
      "buy_price": 0.00226,
      "sell_on": "kucoin",
      "sell_price": 0.003001,
      "profit_pct": 32.7876
    },
    {
      "symbol": "AAVE3S/USDT",
      "buy_on": "gateio",
      "buy_price": 0.0627,
      "sell_on": "kucoin",
      "sell_price": 0.0829,
      "profit_pct": 32.2169
    },
    {
      "symbol": "CLV/USDT",
      "buy_on": "gateio",
      "buy_price": 0.008392,
      "sell_on": "kucoin",
      "sell_price": 0.01098,
      "profit_pct": 30.8389
    },
    {
      "symbol": "ADA3S/USDT",
      "buy_on": "gateio",
      "buy_price": 1.3628,
      "sell_on": "kucoin",
      "sell_price": 1.7764,
      "profit_pct": 30.3493
    },
    {
      "symbol": "DIN/USDT",
      "buy_on": "kucoin",
      "buy_price": 0.1033,
      "sell_on": "gateio",
      "sell_price": 0.12827,
      "profit_pct": 24.1723
    },
    {
      "symbol": "CELB/USDT",
      "buy_on": "gateio",
      "buy_price": 0.0002438,
      "sell_on": "kucoin",
      "sell_price": 0.000301,
      "profit_pct": 23.4619
    },
    {
      "symbol": "XRP3L/USDT",
      "buy_on": "kucoin",
      "buy_price": 1.0312,
      "sell_on": "gateio",
      "sell_price": 1.1367,
      "profit_pct": 10.2308
    },
    {
      "symbol": "MAHA/USDT",
      "buy_on": "gateio",
      "buy_price": 0.1221,
      "sell_on": "kucoin",
      "sell_price": 0.1293,
      "profit_pct": 5.8968
    },
    {
      "symbol": "BRAWL/USDT",
      "buy_on": "gateio",
      "buy_price": 1.498e-05,
      "sell_on": "kucoin",
      "sell_price": 1.585e-05,
      "profit_pct": 5.8077
    },
    {
      "symbol": "RWA/USDT",
      "buy_on": "kucoin",
      "buy_price": 0.004041,
      "sell_on": "gateio",
      "sell_price": 0.004271,
      "profit_pct": 5.6917
    },
    {
      "symbol": "BLOCK/USDT",
      "buy_on": "gateio",
      "buy_price": 0.0002837,
      "sell_on": "kucoin",
      "sell_price": 0.000298,
      "profit_pct": 5.0405
    },
    {
      "symbol": "GOATS/USDT",
      "buy_on": "kucoin",
      "buy_price": 4.592e-05,
      "sell_on": "gateio",
      "sell_price": 4.808e-05,
      "profit_pct": 4.7038
    },
    {
      "symbol": "DEFI/USDT",
      "buy_on": "kucoin",
      "buy_price": 0.000855,
      "sell_on": "gateio",
      "sell_price": 0.0008909,
      "profit_pct": 4.1988
    },
    {
      "symbol": "NLK/USDT",
      "buy_on": "gateio",
      "buy_price": 0.0009177,
      "sell_on": "kucoin",
      "sell_price": 0.0009443,
      "profit_pct": 2.8986
    },
    {
      "symbol": "NEAR3L/USDT",
      "buy_on": "kucoin",
      "buy_price": 0.6476,
      "sell_on": "gateio",
      "sell_price": 0.665,
      "profit_pct": 2.6868
    },
    {
      "symbol": "MYRIA/USDT",
      "buy_on": "gateio",
      "buy_price": 0.000284,
      "sell_on": "kucoin",
      "sell_price": 0.000291,
      "profit_pct": 2.4648
    },
    {
      "symbol": "CATS/USDT",
      "buy_on": "gateio",
      "buy_price": 5.417e-07,
      "sell_on": "kucoin",
      "sell_price": 5.534e-07,
      "profit_pct": 2.1599
    },
    {
      "symbol": "NUMI/USDT",
      "buy_on": "gateio",
      "buy_price": 0.09057,
      "sell_on": "kucoin",
      "sell_price": 0.09225,
      "profit_pct": 1.8549
    },
    {
      "symbol": "XYRO/USDT",
      "buy_on": "kucoin",
      "buy_price": 0.00047,
      "sell_on": "gateio",
      "sell_price": 0.0004787,
      "profit_pct": 1.8511
    },
    {
      "symbol": "VENOM/USDT",
      "buy_on": "gateio",
      "buy_price": 0.066,
      "sell_on": "kucoin",
      "sell_price": 0.0672,
      "profit_pct": 1.8182
    },
    {
      "symbol": "MARSH/USDT",
      "buy_on": "kucoin",
      "buy_price": 0.006445,
      "sell_on": "gateio",
      "sell_price": 0.006551,
      "profit_pct": 1.6447
    },
    {
      "symbol": "HIFI/USDT",
      "buy_on": "kucoin",
      "buy_price": 0.0441,
      "sell_on": "gateio",
      "sell_price": 0.0448,
      "profit_pct": 1.5873
    },
    {
      "symbol": "GODL/USDT",
      "buy_on": "gateio",
      "buy_price": 0.000221,
      "sell_on": "kucoin",
      "sell_price": 0.0002241,
      "profit_pct": 1.4027
    },
    {
      "symbol": "G7/USDT",
      "buy_on": "kucoin",
      "buy_price": 0.000181,
      "sell_on": "gateio",
      "sell_price": 0.0001832,
      "profit_pct": 1.2155
    },
    {
      "symbol": "TRVL/USDT",
      "buy_on": "kucoin",
      "buy_price": 0.004785,
      "sell_on": "gateio",
      "sell_price": 0.004837,
      "profit_pct": 1.0867
    },
    {
      "symbol": "XEM/USDT",
      "buy_on": "gateio",
      "buy_price": 0.0011315,
      "sell_on": "kucoin",
      "sell_price": 0.001143,
      "profit_pct": 1.0163
    },
    {
      "symbol": "DFYN/USDT",
      "buy_on": "kucoin",
      "buy_price": 0.002541,
      "sell_on": "gateio",
      "sell_price": 0.002566,
      "profit_pct": 0.9839
    },
    {
      "symbol": "INC/USDT",
      "buy_on": "kucoin",
      "buy_price": 0.5245,
      "sell_on": "gateio",
      "sell_price": 0.5296,
      "profit_pct": 0.9724
    },
    {
      "symbol": "MTV/USDT",
      "buy_on": "gateio",
      "buy_price": 0.0003304,
      "sell_on": "kucoin",
      "sell_price": 0.0003335,
      "profit_pct": 0.9383
    },
    {
      "symbol": "SYNT/USDT",
      "buy_on": "kucoin",
      "buy_price": 0.00689,
      "sell_on": "gateio",
      "sell_price": 0.006951,
      "profit_pct": 0.8853
    },
    {
      "symbol": "XEN/USDT",
      "buy_on": "gateio",
      "buy_price": 1.836e-08,
      "sell_on": "kucoin",
      "sell_price": 1.851e-08,
      "profit_pct": 0.817
    },
    {
      "symbol": "XTAG/USDT",
      "buy_on": "kucoin",
      "buy_price": 0.00626,
      "sell_on": "gateio",
      "sell_price": 0.00631,
      "profit_pct": 0.7987
    },
    {
      "symbol": "PUSH/USDT",
      "buy_on": "gateio",
      "buy_price": 0.01412,
      "sell_on": "kucoin",
      "sell_price": 0.01423,
      "profit_pct": 0.779
    },
    {
      "symbol": "MTRG/USDT",
      "buy_on": "kucoin",
      "buy_price": 0.08045,
      "sell_on": "gateio",
      "sell_price": 0.08107,
      "profit_pct": 0.7707
    },
    {
      "symbol": "APP/USDT",
      "buy_on": "gateio",
      "buy_price": 0.000784,
      "sell_on": "kucoin",
      "sell_price": 0.00079,
      "profit_pct": 0.7653
    },
    {
      "symbol": "CWS/USDT",
      "buy_on": "gateio",
      "buy_price": 0.09766,
      "sell_on": "kucoin",
      "sell_price": 0.0984,
      "profit_pct": 0.7577
    },
    {
      "symbol": "GMRX/USDT",
      "buy_on": "kucoin",
      "buy_price": 4.07e-05,
      "sell_on": "gateio",
      "sell_price": 4.097e-05,
      "profit_pct": 0.6634
    },
    {
      "symbol": "YB/USDT",
      "buy_on": "kucoin",
      "buy_price": 0.5396,
      "sell_on": "gateio",
      "sell_price": 0.543,
      "profit_pct": 0.6301
    },
    {
      "symbol": "UNITE/USDT",
      "buy_on": "gateio",
      "buy_price": 0.0002913,
      "sell_on": "kucoin",
      "sell_price": 0.0002931,
      "profit_pct": 0.6179
    },
    {
      "symbol": "PERP/USDT",
      "buy_on": "gateio",
      "buy_price": 0.1384,
      "sell_on": "kucoin",
      "sell_price": 0.1392,
      "profit_pct": 0.578
    },
    {
      "symbol": "UAI/USDT",
      "buy_on": "kucoin",
      "buy_price": 0.11982,
      "sell_on": "gateio",
      "sell_price": 0.1205,
      "profit_pct": 0.5675
    },
    {
      "symbol": "LOFI/USDT",
      "buy_on": "gateio",
      "buy_price": 0.011249,
      "sell_on": "kucoin",
      "sell_price": 0.01131,
      "profit_pct": 0.5423
    },
    {
      "symbol": "HARD/USDT",
      "buy_on": "kucoin",
      "buy_price": 0.005035,
      "sell_on": "gateio",
      "sell_price": 0.005062,
      "profit_pct": 0.5362
    },
    {
      "symbol": "TRVL/BTC",
      "buy_on": "kucoin",
      "buy_price": 4.7e-08,
      "sell_on": "gateio",
      "sell_price": 4.725e-08,
      "profit_pct": 0.5319
    },
    {
      "symbol": "HTR/USDT",
      "buy_on": "gateio",
      "buy_price": 0.0207,
      "sell_on": "kucoin",
      "sell_price": 0.02081,
      "profit_pct": 0.5314
    },
    {
      "symbol": "PBX/USDT",
      "buy_on": "gateio",
      "buy_price": 5.969e-05,
      "sell_on": "kucoin",
      "sell_price": 6e-05,
      "profit_pct": 0.5193
    },
    {
      "symbol": "BSV/USDT",
      "buy_on": "gateio",
      "buy_price": 23.29,
      "sell_on": "kucoin",
      "sell_price": 23.41,
      "profit_pct": 0.5152
    },
    {
      "symbol": "OVR/USDT",
      "buy_on": "gateio",
      "buy_price": 0.079,
      "sell_on": "kucoin",
      "sell_price": 0.0794,
      "profit_pct": 0.5063
    },
    {
      "symbol": "ARTFI/USDT",
      "buy_on": "gateio",
      "buy_price": 0.002699,
      "sell_on": "kucoin",
      "sell_price": 0.002712,
      "profit_pct": 0.4817
    },
    {
      "symbol": "XRD/USDT",
      "buy_on": "gateio",
      "buy_price": 0.002307,
      "sell_on": "kucoin",
      "sell_price": 0.002318,
      "profit_pct": 0.4768
    },
    {
      "symbol": "NODE/USDT",
      "buy_on": "kucoin",
      "buy_price": 0.04798,
      "sell_on": "gateio",
      "sell_price": 0.0482,
      "profit_pct": 0.4585
    },
    {
      "symbol": "BUZZ/USDT",
      "buy_on": "kucoin",
      "buy_price": 0.001969,
      "sell_on": "gateio",
      "sell_price": 0.001978,
      "profit_pct": 0.4571
    },
    {
      "symbol": "BOOM/USDT",
      "buy_on": "kucoin",
      "buy_price": 0.01602,
      "sell_on": "gateio",
      "sell_price": 0.01609,
      "profit_pct": 0.437
    },
    {
      "symbol": "CHEEMS/USDT",
      "buy_on": "kucoin",
      "buy_price": 1.2654e-06,
      "sell_on": "gateio",
      "sell_price": 1.2709e-06,
      "profit_pct": 0.4346
    },
    {
      "symbol": "KLINK/USDT",
      "buy_on": "gateio",
      "buy_price": 0.01709,
      "sell_on": "kucoin",
      "sell_price": 0.01716,
      "profit_pct": 0.4096
    },
    {
      "symbol": "EYWA/USDT",
      "buy_on": "kucoin",
      "buy_price": 0.002268,
      "sell_on": "gateio",
      "sell_price": 0.002277,
      "profit_pct": 0.3968
    },
    {
      "symbol": "SOON/USDT",
      "buy_on": "kucoin",
      "buy_price": 1.4473,
      "sell_on": "gateio",
      "sell_price": 1.4529,
      "profit_pct": 0.3869
    },
    {
      "symbol": "MOZ/USDT",
      "buy_on": "gateio",
      "buy_price": 0.0002088,
      "sell_on": "kucoin",
      "sell_price": 0.0002096,
      "profit_pct": 0.3831
    },
    {
      "symbol": "TEVA/USDT",
      "buy_on": "kucoin",
      "buy_price": 0.002493,
      "sell_on": "gateio",
      "sell_price": 0.002502,
      "profit_pct": 0.361
    },
    {
      "symbol": "VEMP/USDT",
      "buy_on": "kucoin",
      "buy_price": 0.0002929,
      "sell_on": "gateio",
      "sell_price": 0.0002939,
      "profit_pct": 0.3414
    },
    {
      "symbol": "WLTH/USDT",
      "buy_on": "kucoin",
      "buy_price": 0.00421,
      "sell_on": "gateio",
      "sell_price": 0.004224,
      "profit_pct": 0.3325
    },
    {
      "symbol": "FORT/USDT",
      "buy_on": "kucoin",
      "buy_price": 0.03326,
      "sell_on": "gateio",
      "sell_price": 0.03337,
      "profit_pct": 0.3307
    },
    {
      "symbol": "SQR/USDT",
      "buy_on": "gateio",
      "buy_price": 0.002538,
      "sell_on": "kucoin",
      "sell_price": 0.002546,
      "profit_pct": 0.3152
    },
    {
      "symbol": "SWEAT/USDT",
      "buy_on": "gateio",
      "buy_price": 0.001598,
      "sell_on": "kucoin",
      "sell_price": 0.001603,
      "profit_pct": 0.3129
    },
    {
      "symbol": "ICE/USDT",
      "buy_on": "kucoin",
      "buy_price": 0.00258,
      "sell_on": "gateio",
      "sell_price": 0.002588,
      "profit_pct": 0.3101
    },
    {
      "symbol": "EGL1/USD1",
      "buy_on": "kucoin",
      "buy_price": 0.02471,
      "sell_on": "gateio",
      "sell_price": 0.02478,
      "profit_pct": 0.2833
    },
    {
      "symbol": "ZEUS/USDT",
      "buy_on": "gateio",
      "buy_price": 0.04338,
      "sell_on": "kucoin",
      "sell_price": 0.0435,
      "profit_pct": 0.2766
    },
    {
      "symbol": "CWEB/USDT",
      "buy_on": "gateio",
      "buy_price": 0.002561,
      "sell_on": "kucoin",
      "sell_price": 0.002568,
      "profit_pct": 0.2733
    },
    {
      "symbol": "ZKWASM/USDT",
      "buy_on": "kucoin",
      "buy_price": 0.0293,
      "sell_on": "gateio",
      "sell_price": 0.02938,
      "profit_pct": 0.273
    },
    {
      "symbol": "PEPE2/USDT",
      "buy_on": "gateio",
      "buy_price": 5.166e-09,
      "sell_on": "kucoin",
      "sell_price": 5.18e-09,
      "profit_pct": 0.271
    },
    {
      "symbol": "EVER/USDT",
      "buy_on": "kucoin",
      "buy_price": 0.00997,
      "sell_on": "gateio",
      "sell_price": 0.009997,
      "profit_pct": 0.2708
    },
    {
      "symbol": "EWT/USDT",
      "buy_on": "kucoin",
      "buy_price": 0.777,
      "sell_on": "gateio",
      "sell_price": 0.7791,
      "profit_pct": 0.2703
    },
    {
      "symbol": "NIM/USDT",
      "buy_on": "gateio",
      "buy_price": 0.0006687,
      "sell_on": "kucoin",
      "sell_price": 0.0006705,
      "profit_pct": 0.2692
    },
    {
      "symbol": "ELP/USDT",
      "buy_on": "gateio",
      "buy_price": 0.003013,
      "sell_on": "kucoin",
      "sell_price": 0.003021,
      "profit_pct": 0.2655
    },
    {
      "symbol": "VLR/USDT",
      "buy_on": "kucoin",
      "buy_price": 0.00763,
      "sell_on": "gateio",
      "sell_price": 0.00765,
      "profit_pct": 0.2621
    },
    {
      "symbol": "SAPIEN/USDT",
      "buy_on": "gateio",
      "buy_price": 0.3525,
      "sell_on": "kucoin",
      "sell_price": 0.35335,
      "profit_pct": 0.2411
    },
    {
      "symbol": "TUSD/USDT",
      "buy_on": "kucoin",
      "buy_price": 0.994,
      "sell_on": "gateio",
      "sell_price": 0.9962,
      "profit_pct": 0.2213
    },
    {
      "symbol": "LAVA/USDT",
      "buy_on": "kucoin",
      "buy_price": 0.1097,
      "sell_on": "gateio",
      "sell_price": 0.10994,
      "profit_pct": 0.2188
    },
    {
      "symbol": "KIP/USDT",
      "buy_on": "kucoin",
      "buy_price": 0.0002312,
      "sell_on": "gateio",
      "sell_price": 0.0002317,
      "profit_pct": 0.2163
    },
    {
      "symbol": "SNX/USDT",
      "buy_on": "kucoin",
      "buy_price": 0.844,
      "sell_on": "gateio",
      "sell_price": 0.8457,
      "profit_pct": 0.2014
    },
    {
      "symbol": "CLOUD/USDT",
      "buy_on": "kucoin",
      "buy_price": 0.0995,
      "sell_on": "gateio",
      "sell_price": 0.0997,
      "profit_pct": 0.201
    }
  ]
}