{
  "status": "success",
  "exchanges_scanned": [
    "binance",
    "kraken",
    "kucoin",
    "gateio",
    "coinbase"
  ],
  "profit_threshold_pct": 0.2,
  "opportunities_found": 71,
  "data": [
    {
      "symbol": "ELON/USDT",
      "buy_on": "kucoin",
      "buy_price": 3.856e-08,
      "sell_on": "gateio",
      "sell_price": 0.0994,
      "profit_pct": 257779982.9876
    },
    {
      "symbol": "HOLD/USDT",
      "buy_on": "gateio",
      "buy_price": 6.242e-06,
      "sell_on": "kucoin",
      "sell_price": 0.2489,
      "profit_pct": 3987404.0051
    },
    {
      "symbol": "BBT/USDT",
      "buy_on": "kucoin",
      "buy_price": 0.00011,
      "sell_on": "gateio",
      "sell_price": 0.13941,
      "profit_pct": 126636.3636
    },
    {
      "symbol": "U/USDT",
      "buy_on": "kucoin",
      "buy_price": 0.000897,
      "sell_on": "gateio",
      "sell_price": 0.9988,
      "profit_pct": 111248.9409
    },
    {
      "symbol": "NEIRO/USDT",
      "buy_on": "gateio",
      "buy_price": 6.571e-05,
      "sell_on": "kucoin",
      "sell_price": 0.000733,
      "profit_pct": 1015.5075
    },
    {
      "symbol": "RVV/USDT",
      "buy_on": "kucoin",
      "buy_price": 0.000186,
      "sell_on": "gateio",
      "sell_price": 0.000861,
      "profit_pct": 362.9032
    },
    {
      "symbol": "VRA/USDT",
      "buy_on": "gateio",
      "buy_price": 2.089e-05,
      "sell_on": "kucoin",
      "sell_price": 9.648e-05,
      "profit_pct": 361.8478
    },
    {
      "symbol": "DIN/USDT",
      "buy_on": "kucoin",
      "buy_price": 0.00935,
      "sell_on": "gateio",
      "sell_price": 0.04119,
      "profit_pct": 340.5348
    },
    {
      "symbol": "MISSION/USDT",
      "buy_on": "gateio",
      "buy_price": 1.222e-07,
      "sell_on": "kucoin",
      "sell_price": 5.03e-07,
      "profit_pct": 311.6203
    },
    {
      "symbol": "BDX/BTC",
      "buy_on": "kucoin",
      "buy_price": 1.143e-06,
      "sell_on": "gateio",
      "sell_price": 2.16735e-06,
      "profit_pct": 89.6194
    },
    {
      "symbol": "BDX/USDT",
      "buy_on": "kucoin",
      "buy_price": 0.07994,
      "sell_on": "gateio",
      "sell_price": 0.15102,
      "profit_pct": 88.9167
    },
    {
      "symbol": "HIFI/USDT",
      "buy_on": "kucoin",
      "buy_price": 0.01059,
      "sell_on": "gateio",
      "sell_price": 0.01562,
      "profit_pct": 47.4976
    },
    {
      "symbol": "TARA/USDT",
      "buy_on": "kucoin",
      "buy_price": 8.65e-05,
      "sell_on": "gateio",
      "sell_price": 0.0001223,
      "profit_pct": 41.3873
    },
    {
      "symbol": "ROOT/USDT",
      "buy_on": "kucoin",
      "buy_price": 0.0001592,
      "sell_on": "gateio",
      "sell_price": 0.0001943,
      "profit_pct": 22.0477
    },
    {
      "symbol": "PTB/USDT",
      "buy_on": "gateio",
      "buy_price": 0.001299,
      "sell_on": "kucoin",
      "sell_price": 0.001415,
      "profit_pct": 8.9299
    },
    {
      "symbol": "MAN/USDT",
      "buy_on": "gateio",
      "buy_price": 0.002332,
      "sell_on": "kucoin",
      "sell_price": 0.002533,
      "profit_pct": 8.6192
    },
    {
      "symbol": "RWA/USDT",
      "buy_on": "kucoin",
      "buy_price": 0.001903,
      "sell_on": "gateio",
      "sell_price": 0.002027,
      "profit_pct": 6.516
    },
    {
      "symbol": "HAPPY/USDT",
      "buy_on": "kucoin",
      "buy_price": 0.000271,
      "sell_on": "gateio",
      "sell_price": 0.0002852,
      "profit_pct": 5.2399
    },
    {
      "symbol": "NFP/USDT",
      "buy_on": "gateio",
      "buy_price": 0.01513,
      "sell_on": "kucoin",
      "sell_price": 0.01588,
      "profit_pct": 4.957
    },
    {
      "symbol": "DPR/USDT",
      "buy_on": "gateio",
      "buy_price": 0.000269,
      "sell_on": "kucoin",
      "sell_price": 0.0002766,
      "profit_pct": 2.8253
    },
    {
      "symbol": "PURR/USDT",
      "buy_on": "gateio",
      "buy_price": 0.08524,
      "sell_on": "kucoin",
      "sell_price": 0.0867,
      "profit_pct": 1.7128
    },
    {
      "symbol": "BCUT/USDT",
      "buy_on": "gateio",
      "buy_price": 0.00286,
      "sell_on": "kucoin",
      "sell_price": 0.002907,
      "profit_pct": 1.6434
    },
    {
      "symbol": "TT/USDT",
      "buy_on": "gateio",
      "buy_price": 0.0008874,
      "sell_on": "kucoin",
      "sell_price": 0.0009,
      "profit_pct": 1.4199
    },
    {
      "symbol": "ULTIMA/USDT",
      "buy_on": "kucoin",
      "buy_price": 4544.38,
      "sell_on": "gateio",
      "sell_price": 4598.7,
      "profit_pct": 1.1953
    },
    {
      "symbol": "XNL/USDT",
      "buy_on": "gateio",
      "buy_price": 0.00026,
      "sell_on": "kucoin",
      "sell_price": 0.0002629,
      "profit_pct": 1.1154
    },
    {
      "symbol": "RCADE/USDT",
      "buy_on": "kucoin",
      "buy_price": 4.47e-05,
      "sell_on": "gateio",
      "sell_price": 4.518e-05,
      "profit_pct": 1.0738
    },
    {
      "symbol": "NRN/USDT",
      "buy_on": "kucoin",
      "buy_price": 0.004969,
      "sell_on": "gateio",
      "sell_price": 0.005022,
      "profit_pct": 1.0666
    },
    {
      "symbol": "CAMP/USDT",
      "buy_on": "kucoin",
      "buy_price": 0.002716,
      "sell_on": "gateio",
      "sell_price": 0.002743,
      "profit_pct": 0.9941
    },
    {
      "symbol": "VANRY/USDT",
      "buy_on": "gateio",
      "buy_price": 0.004766,
      "sell_on": "kucoin",
      "sell_price": 0.00481,
      "profit_pct": 0.9232
    },
    {
      "symbol": "PHIL/USDT",
      "buy_on": "gateio",
      "buy_price": 0.0004935,
      "sell_on": "kucoin",
      "sell_price": 0.000498,
      "profit_pct": 0.9119
    },
    {
      "symbol": "NIM/USDT",
      "buy_on": "gateio",
      "buy_price": 0.0005823,
      "sell_on": "kucoin",
      "sell_price": 0.0005875,
      "profit_pct": 0.893
    },
    {
      "symbol": "CCD/USDT",
      "buy_on": "kucoin",
      "buy_price": 0.005055,
      "sell_on": "gateio",
      "sell_price": 0.005095,
      "profit_pct": 0.7913
    },
    {
      "symbol": "ZCX/USDT",
      "buy_on": "gateio",
      "buy_price": 0.003505,
      "sell_on": "kucoin",
      "sell_price": 0.00353,
      "profit_pct": 0.7133
    },
    {
      "symbol": "EQTY/USDT",
      "buy_on": "gateio",
      "buy_price": 0.0029,
      "sell_on": "kucoin",
      "sell_price": 0.00292,
      "profit_pct": 0.6897
    },
    {
      "symbol": "G3/USDT",
      "buy_on": "kucoin",
      "buy_price": 0.0002558,
      "sell_on": "gateio",
      "sell_price": 0.0002575,
      "profit_pct": 0.6646
    },
    {
      "symbol": "MAIGA/USDT",
      "buy_on": "kucoin",
      "buy_price": 0.00268,
      "sell_on": "gateio",
      "sell_price": 0.002697,
      "profit_pct": 0.6343
    },
    {
      "symbol": "FLIP/USDT",
      "buy_on": "kucoin",
      "buy_price": 0.2625,
      "sell_on": "gateio",
      "sell_price": 0.2641,
      "profit_pct": 0.6095
    },
    {
      "symbol": "KITE/USDT",
      "buy_on": "kucoin",
      "buy_price": 0.27907,
      "sell_on": "gateio",
      "sell_price": 0.28072,
      "profit_pct": 0.5912
    },
    {
      "symbol": "MAJOR/USDT",
      "buy_on": "kucoin",
      "buy_price": 0.06317,
      "sell_on": "gateio",
      "sell_price": 0.0635,
      "profit_pct": 0.5224
    },
    {
      "symbol": "AITECH/USDT",
      "buy_on": "kucoin",
      "buy_price": 0.005908,
      "sell_on": "gateio",
      "sell_price": 0.005937,
      "profit_pct": 0.4909
    },
    {
      "symbol": "VOOI/USDT",
      "buy_on": "kucoin",
      "buy_price": 0.004897,
      "sell_on": "gateio",
      "sell_price": 0.004921,
      "profit_pct": 0.4901
    },
    {
      "symbol": "ITHACA/USDT",
      "buy_on": "gateio",
      "buy_price": 0.003229,
      "sell_on": "kucoin",
      "sell_price": 0.0032443,
      "profit_pct": 0.4738
    },
    {
      "symbol": "ELIZAOS/USDT",
      "buy_on": "gateio",
      "buy_price": 0.001082,
      "sell_on": "kucoin",
      "sell_price": 0.001087,
      "profit_pct": 0.4621
    },
    {
      "symbol": "ELA/USDT",
      "buy_on": "gateio",
      "buy_price": 0.57,
      "sell_on": "kucoin",
      "sell_price": 0.5725,
      "profit_pct": 0.4386
    },
    {
      "symbol": "IOST/USDT",
      "buy_on": "gateio",
      "buy_price": 0.00115,
      "sell_on": "kucoin",
      "sell_price": 0.001155,
      "profit_pct": 0.4348
    },
    {
      "symbol": "VAIOT/USDT",
      "buy_on": "kucoin",
      "buy_price": 0.00672,
      "sell_on": "gateio",
      "sell_price": 0.006749,
      "profit_pct": 0.4315
    },
    {
      "symbol": "ARTY/USDT",
      "buy_on": "gateio",
      "buy_price": 0.08285,
      "sell_on": "kucoin",
      "sell_price": 0.0832,
      "profit_pct": 0.4225
    },
    {
      "symbol": "STREAM/USDT",
      "buy_on": "kucoin",
      "buy_price": 0.00741,
      "sell_on": "gateio",
      "sell_price": 0.007437,
      "profit_pct": 0.3644
    },
    {
      "symbol": "EMYC/USDT",
      "buy_on": "gateio",
      "buy_price": 0.005567,
      "sell_on": "kucoin",
      "sell_price": 0.005587,
      "profit_pct": 0.3593
    },
    {
      "symbol": "MILADYCULT/USDT",
      "buy_on": "kucoin",
      "buy_price": 0.0001672,
      "sell_on": "gateio",
      "sell_price": 0.0001678,
      "profit_pct": 0.3589
    },
    {
      "symbol": "BNC/USDT",
      "buy_on": "kucoin",
      "buy_price": 0.03704,
      "sell_on": "gateio",
      "sell_price": 0.03717,
      "profit_pct": 0.351
    },
    {
      "symbol": "LKI/USDT",
      "buy_on": "kucoin",
      "buy_price": 0.0004279,
      "sell_on": "gateio",
      "sell_price": 0.0004294,
      "profit_pct": 0.3505
    },
    {
      "symbol": "TEVA/USDT",
      "buy_on": "gateio",
      "buy_price": 0.0007474,
      "sell_on": "kucoin",
      "sell_price": 0.00075,
      "profit_pct": 0.3479
    },
    {
      "symbol": "RIZ/USDT",
      "buy_on": "gateio",
      "buy_price": 0.0002042,
      "sell_on": "kucoin",
      "sell_price": 0.0002049,
      "profit_pct": 0.3428
    },
    {
      "symbol": "XRD/USDT",
      "buy_on": "kucoin",
      "buy_price": 0.001761,
      "sell_on": "gateio",
      "sell_price": 0.001767,
      "profit_pct": 0.3407
    },
    {
      "symbol": "CWEB/USDT",
      "buy_on": "gateio",
      "buy_price": 0.001206,
      "sell_on": "kucoin",
      "sell_price": 0.00121,
      "profit_pct": 0.3317
    },
    {
      "symbol": "VENOM/USDT",
      "buy_on": "kucoin",
      "buy_price": 0.0244,
      "sell_on": "gateio",
      "sell_price": 0.02448,
      "profit_pct": 0.3279
    },
    {
      "symbol": "SPA/USDT",
      "buy_on": "kucoin",
      "buy_price": 0.003464,
      "sell_on": "gateio",
      "sell_price": 0.003475,
      "profit_pct": 0.3176
    },
    {
      "symbol": "ISP/USDT",
      "buy_on": "gateio",
      "buy_price": 6.749e-05,
      "sell_on": "kucoin",
      "sell_price": 6.77e-05,
      "profit_pct": 0.3112
    },
    {
      "symbol": "ZEUS/USDT",
      "buy_on": "gateio",
      "buy_price": 0.009003,
      "sell_on": "kucoin",
      "sell_price": 0.00903,
      "profit_pct": 0.2999
    },
    {
      "symbol": "PIN/USDT",
      "buy_on": "gateio",
      "buy_price": 0.09692,
      "sell_on": "kucoin",
      "sell_price": 0.0972,
      "profit_pct": 0.2889
    },
    {
      "symbol": "PROPS/USDT",
      "buy_on": "kucoin",
      "buy_price": 0.005575,
      "sell_on": "gateio",
      "sell_price": 0.005591,
      "profit_pct": 0.287
    },
    {
      "symbol": "UMA/USDT",
      "buy_on": "gateio",
      "buy_price": 0.4218,
      "sell_on": "kucoin",
      "sell_price": 0.423,
      "profit_pct": 0.2845
    },
    {
      "symbol": "MTRG/USDT",
      "buy_on": "gateio",
      "buy_price": 0.02165,
      "sell_on": "kucoin",
      "sell_price": 0.02171,
      "profit_pct": 0.2771
    },
    {
      "symbol": "EGL1/USD1",
      "buy_on": "gateio",
      "buy_price": 0.03689,
      "sell_on": "kucoin",
      "sell_price": 0.03699,
      "profit_pct": 0.2711
    },
    {
      "symbol": "NATIX/USDT",
      "buy_on": "gateio",
      "buy_price": 0.00010064,
      "sell_on": "kucoin",
      "sell_price": 0.0001009,
      "profit_pct": 0.2583
    },
    {
      "symbol": "XION/USDT",
      "buy_on": "kucoin",
      "buy_price": 0.112,
      "sell_on": "gateio",
      "sell_price": 0.11228,
      "profit_pct": 0.25
    },
    {
      "symbol": "AVNT/USDT",
      "buy_on": "gateio",
      "buy_price": 0.15079,
      "sell_on": "kucoin",
      "sell_price": 0.15116,
      "profit_pct": 0.2454
    },
    {
      "symbol": "HEART/USDT",
      "buy_on": "kucoin",
      "buy_price": 0.000758,
      "sell_on": "gateio",
      "sell_price": 0.0007598,
      "profit_pct": 0.2375
    },
    {
      "symbol": "SENSO/USDT",
      "buy_on": "gateio",
      "buy_price": 0.003041,
      "sell_on": "kucoin",
      "sell_price": 0.003048,
      "profit_pct": 0.2302
    },
    {
      "symbol": "XYO/USDT",
      "buy_on": "gateio",
      "buy_price": 0.004082,
      "sell_on": "kucoin",
      "sell_price": 0.004091,
      "profit_pct": 0.2205
    }
  ]
}