{
  "status": "success",
  "exchanges_scanned": [
    "binance",
    "kraken",
    "kucoin",
    "gateio",
    "coinbase"
  ],
  "profit_threshold_pct": 0.2,
  "opportunities_found": 119,
  "data": [
    {
      "symbol": "HOLD/USDT",
      "buy_on": "gateio",
      "buy_price": 1.022e-05,
      "sell_on": "kucoin",
      "sell_price": 1.7468,
      "profit_pct": 17091876.5166
    },
    {
      "symbol": "MAX/USDT",
      "buy_on": "kucoin",
      "buy_price": 0.00848,
      "sell_on": "gateio",
      "sell_price": 583.47,
      "profit_pct": 6880442.4528
    },
    {
      "symbol": "POP/USDT",
      "buy_on": "gateio",
      "buy_price": 1.4513e-07,
      "sell_on": "kucoin",
      "sell_price": 0.009574,
      "profit_pct": 6596744.2086
    },
    {
      "symbol": "DOT3S/USDT",
      "buy_on": "kucoin",
      "buy_price": 3.402e-05,
      "sell_on": "gateio",
      "sell_price": 2.201,
      "profit_pct": 6469623.6919
    },
    {
      "symbol": "ACE/USDT",
      "buy_on": "kucoin",
      "buy_price": 8.39e-05,
      "sell_on": "gateio",
      "sell_price": 0.4723,
      "profit_pct": 562832.062
    },
    {
      "symbol": "ZERO/USDT",
      "buy_on": "kucoin",
      "buy_price": 3.37e-05,
      "sell_on": "gateio",
      "sell_price": 0.13092,
      "profit_pct": 388386.6469
    },
    {
      "symbol": "TAP/USDT",
      "buy_on": "gateio",
      "buy_price": 0.0001584,
      "sell_on": "kucoin",
      "sell_price": 0.415,
      "profit_pct": 261894.9495
    },
    {
      "symbol": "ARB3S/USDT",
      "buy_on": "kucoin",
      "buy_price": 0.00017336,
      "sell_on": "gateio",
      "sell_price": 0.3873,
      "profit_pct": 223307.9372
    },
    {
      "symbol": "BTC3L/USDT",
      "buy_on": "kucoin",
      "buy_price": 0.013302,
      "sell_on": "gateio",
      "sell_price": 16.8872,
      "profit_pct": 126852.338
    },
    {
      "symbol": "SUSHI3S/USDT",
      "buy_on": "kucoin",
      "buy_price": 0.00010264,
      "sell_on": "gateio",
      "sell_price": 0.11375,
      "profit_pct": 110724.2401
    },
    {
      "symbol": "SUSHI3L/USDT",
      "buy_on": "kucoin",
      "buy_price": 0.001237,
      "sell_on": "gateio",
      "sell_price": 1.1197,
      "profit_pct": 90417.3808
    },
    {
      "symbol": "DOT3L/USDT",
      "buy_on": "kucoin",
      "buy_price": 0.004104,
      "sell_on": "gateio",
      "sell_price": 2.286,
      "profit_pct": 55601.7544
    },
    {
      "symbol": "BTC3S/USDT",
      "buy_on": "kucoin",
      "buy_price": 7.538e-05,
      "sell_on": "gateio",
      "sell_price": 0.03846,
      "profit_pct": 50921.4911
    },
    {
      "symbol": "BNB3S/USDT",
      "buy_on": "kucoin",
      "buy_price": 2.189e-05,
      "sell_on": "gateio",
      "sell_price": 0.007784,
      "profit_pct": 35459.6163
    },
    {
      "symbol": "LINK3S/USDT",
      "buy_on": "kucoin",
      "buy_price": 0.003146,
      "sell_on": "gateio",
      "sell_price": 1.1017,
      "profit_pct": 34919.0718
    },
    {
      "symbol": "ADA3S/USDT",
      "buy_on": "kucoin",
      "buy_price": 0.007043,
      "sell_on": "gateio",
      "sell_price": 2.023,
      "profit_pct": 28623.5553
    },
    {
      "symbol": "NEAR3S/USDT",
      "buy_on": "kucoin",
      "buy_price": 6.352e-05,
      "sell_on": "gateio",
      "sell_price": 0.01568,
      "profit_pct": 24585.1385
    },
    {
      "symbol": "DOGE3S/USDT",
      "buy_on": "kucoin",
      "buy_price": 2.937e-05,
      "sell_on": "gateio",
      "sell_price": 0.006731,
      "profit_pct": 22817.9435
    },
    {
      "symbol": "AVAX3S/USDT",
      "buy_on": "kucoin",
      "buy_price": 0.001531,
      "sell_on": "gateio",
      "sell_price": 0.2925,
      "profit_pct": 19005.16
    },
    {
      "symbol": "XRP3S/USDT",
      "buy_on": "kucoin",
      "buy_price": 0.006177,
      "sell_on": "gateio",
      "sell_price": 1.01781,
      "profit_pct": 16377.4162
    },
    {
      "symbol": "BCH3S/USDT",
      "buy_on": "kucoin",
      "buy_price": 0.00309,
      "sell_on": "gateio",
      "sell_price": 0.411,
      "profit_pct": 13200.9709
    },
    {
      "symbol": "ADA3L/USDT",
      "buy_on": "kucoin",
      "buy_price": 0.00066771,
      "sell_on": "gateio",
      "sell_price": 0.06139,
      "profit_pct": 9094.1112
    },
    {
      "symbol": "UNI3S/USDT",
      "buy_on": "kucoin",
      "buy_price": 0.006687,
      "sell_on": "gateio",
      "sell_price": 0.50609,
      "profit_pct": 7468.2668
    },
    {
      "symbol": "ETH3S/USDT",
      "buy_on": "kucoin",
      "buy_price": 0.003756,
      "sell_on": "gateio",
      "sell_price": 0.2522,
      "profit_pct": 6614.59
    },
    {
      "symbol": "LINK3L/USDT",
      "buy_on": "kucoin",
      "buy_price": 0.1862,
      "sell_on": "gateio",
      "sell_price": 9.476,
      "profit_pct": 4989.1515
    },
    {
      "symbol": "LAYER/USDT",
      "buy_on": "kucoin",
      "buy_price": 0.00978,
      "sell_on": "gateio",
      "sell_price": 0.4153,
      "profit_pct": 4146.4213
    },
    {
      "symbol": "SUI3L/USDT",
      "buy_on": "kucoin",
      "buy_price": 0.000971,
      "sell_on": "gateio",
      "sell_price": 0.03997,
      "profit_pct": 4016.3749
    },
    {
      "symbol": "APE3L/USDT",
      "buy_on": "kucoin",
      "buy_price": 0.000768,
      "sell_on": "gateio",
      "sell_price": 0.02786,
      "profit_pct": 3527.6042
    },
    {
      "symbol": "SOL3L/USDT",
      "buy_on": "kucoin",
      "buy_price": 0.37371262,
      "sell_on": "gateio",
      "sell_price": 12.227,
      "profit_pct": 3171.7653
    },
    {
      "symbol": "AVAX3L/USDT",
      "buy_on": "kucoin",
      "buy_price": 0.00461866,
      "sell_on": "gateio",
      "sell_price": 0.1007,
      "profit_pct": 2080.2861
    },
    {
      "symbol": "ARB3L/USDT",
      "buy_on": "gateio",
      "buy_price": 0.065,
      "sell_on": "kucoin",
      "sell_price": 1.0692,
      "profit_pct": 1544.9231
    },
    {
      "symbol": "VET3S/USDT",
      "buy_on": "kucoin",
      "buy_price": 0.1003,
      "sell_on": "gateio",
      "sell_price": 1.628,
      "profit_pct": 1523.1306
    },
    {
      "symbol": "BCH3L/USDT",
      "buy_on": "gateio",
      "buy_price": 0.08903,
      "sell_on": "kucoin",
      "sell_price": 1.430564,
      "profit_pct": 1506.8337
    },
    {
      "symbol": "AAVE3L/USDT",
      "buy_on": "kucoin",
      "buy_price": 0.0265499,
      "sell_on": "gateio",
      "sell_price": 0.3238,
      "profit_pct": 1119.5903
    },
    {
      "symbol": "NEIRO/USDT",
      "buy_on": "gateio",
      "buy_price": 0.0006071,
      "sell_on": "kucoin",
      "sell_price": 0.0065,
      "profit_pct": 970.6638
    },
    {
      "symbol": "AAVE3S/USDT",
      "buy_on": "gateio",
      "buy_price": 0.22677,
      "sell_on": "kucoin",
      "sell_price": 1.8772,
      "profit_pct": 727.7991
    },
    {
      "symbol": "SUI3S/USDT",
      "buy_on": "kucoin",
      "buy_price": 0.001229,
      "sell_on": "gateio",
      "sell_price": 0.00959,
      "profit_pct": 680.3092
    },
    {
      "symbol": "UNI3L/USDT",
      "buy_on": "kucoin",
      "buy_price": 0.00144442,
      "sell_on": "gateio",
      "sell_price": 0.009615,
      "profit_pct": 565.6651
    },
    {
      "symbol": "QI/USDT",
      "buy_on": "gateio",
      "buy_price": 0.001703,
      "sell_on": "kucoin",
      "sell_price": 0.008163,
      "profit_pct": 379.3306
    },
    {
      "symbol": "SMILE/USDT",
      "buy_on": "gateio",
      "buy_price": 0.003766,
      "sell_on": "kucoin",
      "sell_price": 0.017,
      "profit_pct": 351.4073
    },
    {
      "symbol": "BROCCOLI/USDT",
      "buy_on": "kucoin",
      "buy_price": 0.00733,
      "sell_on": "gateio",
      "sell_price": 0.03213,
      "profit_pct": 338.3356
    },
    {
      "symbol": "ETH3L/USDT",
      "buy_on": "gateio",
      "buy_price": 3.8343,
      "sell_on": "kucoin",
      "sell_price": 13.4754,
      "profit_pct": 251.4435
    },
    {
      "symbol": "ATOM3L/USDT",
      "buy_on": "kucoin",
      "buy_price": 0.002347,
      "sell_on": "gateio",
      "sell_price": 0.007839,
      "profit_pct": 234.0009
    },
    {
      "symbol": "ATOM3S/USDT",
      "buy_on": "kucoin",
      "buy_price": 0.5019,
      "sell_on": "gateio",
      "sell_price": 1.4792,
      "profit_pct": 194.7201
    },
    {
      "symbol": "LTC3S/USDT",
      "buy_on": "kucoin",
      "buy_price": 0.2459,
      "sell_on": "gateio",
      "sell_price": 0.69457,
      "profit_pct": 182.4603
    },
    {
      "symbol": "AIPUMP/USDT",
      "buy_on": "gateio",
      "buy_price": 0.0003886,
      "sell_on": "kucoin",
      "sell_price": 0.000811,
      "profit_pct": 108.6979
    },
    {
      "symbol": "LTC3L/USDT",
      "buy_on": "gateio",
      "buy_price": 0.18926,
      "sell_on": "kucoin",
      "sell_price": 0.3693,
      "profit_pct": 95.1284
    },
    {
      "symbol": "GST/USDT",
      "buy_on": "gateio",
      "buy_price": 0.002528,
      "sell_on": "kucoin",
      "sell_price": 0.00481,
      "profit_pct": 90.269
    },
    {
      "symbol": "BNB3L/USDT",
      "buy_on": "kucoin",
      "buy_price": 0.5481,
      "sell_on": "gateio",
      "sell_price": 1.0297,
      "profit_pct": 87.8672
    },
    {
      "symbol": "MINT/USDT",
      "buy_on": "kucoin",
      "buy_price": 0.001759,
      "sell_on": "gateio",
      "sell_price": 0.003132,
      "profit_pct": 78.0557
    },
    {
      "symbol": "RPK/USDT",
      "buy_on": "gateio",
      "buy_price": 0.000239,
      "sell_on": "kucoin",
      "sell_price": 0.00038,
      "profit_pct": 58.9958
    },
    {
      "symbol": "DIN/USDT",
      "buy_on": "gateio",
      "buy_price": 0.03901,
      "sell_on": "kucoin",
      "sell_price": 0.0574,
      "profit_pct": 47.1418
    },
    {
      "symbol": "VET3L/USDT",
      "buy_on": "gateio",
      "buy_price": 0.02565,
      "sell_on": "kucoin",
      "sell_price": 0.036336,
      "profit_pct": 41.6608
    },
    {
      "symbol": "GOATS/USDT",
      "buy_on": "kucoin",
      "buy_price": 5.37e-05,
      "sell_on": "gateio",
      "sell_price": 7.501e-05,
      "profit_pct": 39.6834
    },
    {
      "symbol": "XRP3L/USDT",
      "buy_on": "kucoin",
      "buy_price": 4.3002,
      "sell_on": "gateio",
      "sell_price": 5.994,
      "profit_pct": 39.3889
    },
    {
      "symbol": "APE3S/USDT",
      "buy_on": "kucoin",
      "buy_price": 0.026694,
      "sell_on": "gateio",
      "sell_price": 0.03689,
      "profit_pct": 38.1958
    },
    {
      "symbol": "POWER/USDT",
      "buy_on": "gateio",
      "buy_price": 0.007736,
      "sell_on": "kucoin",
      "sell_price": 0.01045,
      "profit_pct": 35.0827
    },
    {
      "symbol": "DEFI/USDT",
      "buy_on": "kucoin",
      "buy_price": 0.001946,
      "sell_on": "gateio",
      "sell_price": 0.002551,
      "profit_pct": 31.0894
    },
    {
      "symbol": "CLV/USDT",
      "buy_on": "gateio",
      "buy_price": 0.013936,
      "sell_on": "kucoin",
      "sell_price": 0.01792,
      "profit_pct": 28.5878
    },
    {
      "symbol": "UNO/USDT",
      "buy_on": "gateio",
      "buy_price": 0.001776,
      "sell_on": "kucoin",
      "sell_price": 0.00219,
      "profit_pct": 23.3108
    },
    {
      "symbol": "BRAWL/USDT",
      "buy_on": "gateio",
      "buy_price": 1.787e-05,
      "sell_on": "kucoin",
      "sell_price": 2.15e-05,
      "profit_pct": 20.3134
    },
    {
      "symbol": "RWA/USDT",
      "buy_on": "gateio",
      "buy_price": 0.007721,
      "sell_on": "kucoin",
      "sell_price": 0.008847,
      "profit_pct": 14.5836
    },
    {
      "symbol": "TAOCAT/USDT",
      "buy_on": "kucoin",
      "buy_price": 0.00048,
      "sell_on": "gateio",
      "sell_price": 0.00054,
      "profit_pct": 12.5
    },
    {
      "symbol": "DOGE3L/USDT",
      "buy_on": "kucoin",
      "buy_price": 0.038666,
      "sell_on": "gateio",
      "sell_price": 0.04347,
      "profit_pct": 12.4244
    },
    {
      "symbol": "MAN/USDT",
      "buy_on": "gateio",
      "buy_price": 0.006091,
      "sell_on": "kucoin",
      "sell_price": 0.006704,
      "profit_pct": 10.064
    },
    {
      "symbol": "SOL3S/USDT",
      "buy_on": "gateio",
      "buy_price": 0.33074,
      "sell_on": "kucoin",
      "sell_price": 0.3506,
      "profit_pct": 6.0047
    },
    {
      "symbol": "BLOCK/USDT",
      "buy_on": "kucoin",
      "buy_price": 0.00046,
      "sell_on": "gateio",
      "sell_price": 0.0004811,
      "profit_pct": 4.587
    },
    {
      "symbol": "SFUND/USDT",
      "buy_on": "gateio",
      "buy_price": 0.2395,
      "sell_on": "kucoin",
      "sell_price": 0.2476,
      "profit_pct": 3.382
    },
    {
      "symbol": "NGL/USDT",
      "buy_on": "gateio",
      "buy_price": 0.008137,
      "sell_on": "kucoin",
      "sell_price": 0.00836,
      "profit_pct": 2.7406
    },
    {
      "symbol": "CELB/USDT",
      "buy_on": "kucoin",
      "buy_price": 0.000483,
      "sell_on": "gateio",
      "sell_price": 0.000495,
      "profit_pct": 2.4845
    },
    {
      "symbol": "JAM/USDT",
      "buy_on": "kucoin",
      "buy_price": 5.53e-05,
      "sell_on": "gateio",
      "sell_price": 5.656e-05,
      "profit_pct": 2.2785
    },
    {
      "symbol": "PFVS/USDT",
      "buy_on": "gateio",
      "buy_price": 0.003883,
      "sell_on": "kucoin",
      "sell_price": 0.00396,
      "profit_pct": 1.983
    },
    {
      "symbol": "MONI/USDT",
      "buy_on": "gateio",
      "buy_price": 0.002029,
      "sell_on": "kucoin",
      "sell_price": 0.002062,
      "profit_pct": 1.6264
    },
    {
      "symbol": "AMPL/USDT",
      "buy_on": "gateio",
      "buy_price": 1.1966,
      "sell_on": "kucoin",
      "sell_price": 1.214,
      "profit_pct": 1.4541
    },
    {
      "symbol": "KIP/USDT",
      "buy_on": "kucoin",
      "buy_price": 0.00041,
      "sell_on": "gateio",
      "sell_price": 0.0004151,
      "profit_pct": 1.2439
    },
    {
      "symbol": "BSV/USDT",
      "buy_on": "gateio",
      "buy_price": 28.88,
      "sell_on": "kucoin",
      "sell_price": 29.19,
      "profit_pct": 1.0734
    },
    {
      "symbol": "NEAR3L/USDT",
      "buy_on": "gateio",
      "buy_price": 3.643,
      "sell_on": "kucoin",
      "sell_price": 3.6757,
      "profit_pct": 0.8976
    },
    {
      "symbol": "SLF/USDT",
      "buy_on": "kucoin",
      "buy_price": 0.0102,
      "sell_on": "gateio",
      "sell_price": 0.01029,
      "profit_pct": 0.8824
    },
    {
      "symbol": "ELP/USDT",
      "buy_on": "gateio",
      "buy_price": 0.002619,
      "sell_on": "kucoin",
      "sell_price": 0.002642,
      "profit_pct": 0.8782
    },
    {
      "symbol": "WEMIX/USDT",
      "buy_on": "gateio",
      "buy_price": 0.6942,
      "sell_on": "kucoin",
      "sell_price": 0.6999,
      "profit_pct": 0.8211
    },
    {
      "symbol": "PIP/USDT",
      "buy_on": "kucoin",
      "buy_price": 0.00052,
      "sell_on": "gateio",
      "sell_price": 0.0005242,
      "profit_pct": 0.8077
    },
    {
      "symbol": "AIO/USDT",
      "buy_on": "kucoin",
      "buy_price": 0.14264,
      "sell_on": "gateio",
      "sell_price": 0.14378,
      "profit_pct": 0.7992
    },
    {
      "symbol": "DMAIL/USDT",
      "buy_on": "gateio",
      "buy_price": 0.03314,
      "sell_on": "kucoin",
      "sell_price": 0.0334,
      "profit_pct": 0.7846
    },
    {
      "symbol": "CATS/USDT",
      "buy_on": "gateio",
      "buy_price": 1.369e-06,
      "sell_on": "kucoin",
      "sell_price": 1.379e-06,
      "profit_pct": 0.7305
    },
    {
      "symbol": "ROOBEE/USDT",
      "buy_on": "gateio",
      "buy_price": 0.0001589,
      "sell_on": "kucoin",
      "sell_price": 0.00016,
      "profit_pct": 0.6923
    },
    {
      "symbol": "XCV/USDT",
      "buy_on": "kucoin",
      "buy_price": 0.000952,
      "sell_on": "gateio",
      "sell_price": 0.0009578,
      "profit_pct": 0.6092
    },
    {
      "symbol": "E4C/USDT",
      "buy_on": "gateio",
      "buy_price": 0.00354,
      "sell_on": "kucoin",
      "sell_price": 0.00356,
      "profit_pct": 0.565
    },
    {
      "symbol": "POLC/USDT",
      "buy_on": "gateio",
      "buy_price": 0.001624,
      "sell_on": "kucoin",
      "sell_price": 0.001632,
      "profit_pct": 0.4926
    },
    {
      "symbol": "XDB/USDT",
      "buy_on": "kucoin",
      "buy_price": 0.00051,
      "sell_on": "gateio",
      "sell_price": 0.0005125,
      "profit_pct": 0.4902
    },
    {
      "symbol": "OBI/USDT",
      "buy_on": "gateio",
      "buy_price": 0.0003742,
      "sell_on": "kucoin",
      "sell_price": 0.000376,
      "profit_pct": 0.481
    },
    {
      "symbol": "WLKN/USDT",
      "buy_on": "gateio",
      "buy_price": 0.0004794,
      "sell_on": "kucoin",
      "sell_price": 0.0004816,
      "profit_pct": 0.4589
    },
    {
      "symbol": "AMB/USDT",
      "buy_on": "kucoin",
      "buy_price": 5.036e-05,
      "sell_on": "gateio",
      "sell_price": 5.057e-05,
      "profit_pct": 0.417
    },
    {
      "symbol": "TUSD/USDT",
      "buy_on": "kucoin",
      "buy_price": 0.9949,
      "sell_on": "gateio",
      "sell_price": 0.999,
      "profit_pct": 0.4121
    },
    {
      "symbol": "VANRY/USDT",
      "buy_on": "gateio",
      "buy_price": 0.02747,
      "sell_on": "kucoin",
      "sell_price": 0.02758,
      "profit_pct": 0.4004
    },
    {
      "symbol": "SQR/USDT",
      "buy_on": "kucoin",
      "buy_price": 0.004952,
      "sell_on": "gateio",
      "sell_price": 0.004971,
      "profit_pct": 0.3837
    },
    {
      "symbol": "MAK/USDT",
      "buy_on": "gateio",
      "buy_price": 0.004075,
      "sell_on": "kucoin",
      "sell_price": 0.00409,
      "profit_pct": 0.3681
    },
    {
      "symbol": "XR/USDT",
      "buy_on": "kucoin",
      "buy_price": 0.01414,
      "sell_on": "gateio",
      "sell_price": 0.01419,
      "profit_pct": 0.3536
    },
    {
      "symbol": "LIKE/USDT",
      "buy_on": "kucoin",
      "buy_price": 0.00997,
      "sell_on": "gateio",
      "sell_price": 0.010003,
      "profit_pct": 0.331
    },
    {
      "symbol": "TRADE/USDT",
      "buy_on": "gateio",
      "buy_price": 0.09718,
      "sell_on": "kucoin",
      "sell_price": 0.0975,
      "profit_pct": 0.3293
    },
    {
      "symbol": "ZELIX/USDT",
      "buy_on": "gateio",
      "buy_price": 1.9329e-05,
      "sell_on": "kucoin",
      "sell_price": 1.939e-05,
      "profit_pct": 0.3156
    },
    {
      "symbol": "BDX/USDT",
      "buy_on": "gateio",
      "buy_price": 0.08057,
      "sell_on": "kucoin",
      "sell_price": 0.08082,
      "profit_pct": 0.3103
    },
    {
      "symbol": "KRL/USDT",
      "buy_on": "kucoin",
      "buy_price": 0.29849,
      "sell_on": "gateio",
      "sell_price": 0.2994,
      "profit_pct": 0.3049
    },
    {
      "symbol": "ROOT/USDT",
      "buy_on": "kucoin",
      "buy_price": 0.001652,
      "sell_on": "gateio",
      "sell_price": 0.001657,
      "profit_pct": 0.3027
    },
    {
      "symbol": "EWT/USDT",
      "buy_on": "kucoin",
      "buy_price": 1.083,
      "sell_on": "gateio",
      "sell_price": 1.0862,
      "profit_pct": 0.2955
    },
    {
      "symbol": "INC/USDT",
      "buy_on": "gateio",
      "buy_price": 0.7515,
      "sell_on": "kucoin",
      "sell_price": 0.7537,
      "profit_pct": 0.2927
    },
    {
      "symbol": "LAY3R/USDT",
      "buy_on": "kucoin",
      "buy_price": 0.008354,
      "sell_on": "gateio",
      "sell_price": 0.008378,
      "profit_pct": 0.2873
    },
    {
      "symbol": "ERG/USDT",
      "buy_on": "gateio",
      "buy_price": 0.7223,
      "sell_on": "kucoin",
      "sell_price": 0.7243,
      "profit_pct": 0.2769
    },
    {
      "symbol": "DPR/USDT",
      "buy_on": "gateio",
      "buy_price": 0.0002234,
      "sell_on": "kucoin",
      "sell_price": 0.000224,
      "profit_pct": 0.2686
    },
    {
      "symbol": "LGCT/USDT",
      "buy_on": "kucoin",
      "buy_price": 1.9338,
      "sell_on": "gateio",
      "sell_price": 1.9389,
      "profit_pct": 0.2637
    },
    {
      "symbol": "FRED/USDT",
      "buy_on": "gateio",
      "buy_price": 0.002325,
      "sell_on": "kucoin",
      "sell_price": 0.002331,
      "profit_pct": 0.2581
    },
    {
      "symbol": "BABYSHARK/USDT",
      "buy_on": "kucoin",
      "buy_price": 0.003138,
      "sell_on": "gateio",
      "sell_price": 0.003146,
      "profit_pct": 0.2549
    },
    {
      "symbol": "XEN/USDT",
      "buy_on": "gateio",
      "buy_price": 3.149e-08,
      "sell_on": "kucoin",
      "sell_price": 3.157e-08,
      "profit_pct": 0.254
    },
    {
      "symbol": "CERE/USDT",
      "buy_on": "kucoin",
      "buy_price": 0.000754,
      "sell_on": "gateio",
      "sell_price": 0.0007559,
      "profit_pct": 0.252
    },
    {
      "symbol": "NPC/USDT",
      "buy_on": "kucoin",
      "buy_price": 0.02012,
      "sell_on": "gateio",
      "sell_price": 0.020169,
      "profit_pct": 0.2435
    },
    {
      "symbol": "XTAG/USDT",
      "buy_on": "gateio",
      "buy_price": 0.0126,
      "sell_on": "kucoin",
      "sell_price": 0.01263,
      "profit_pct": 0.2381
    },
    {
      "symbol": "TRVL/USDT",
      "buy_on": "kucoin",
      "buy_price": 0.007735,
      "sell_on": "gateio",
      "sell_price": 0.007753,
      "profit_pct": 0.2327
    },
    {
      "symbol": "LOOKS/USDT",
      "buy_on": "gateio",
      "buy_price": 0.013968,
      "sell_on": "kucoin",
      "sell_price": 0.014,
      "profit_pct": 0.2291
    },
    {
      "symbol": "GAFI/USDT",
      "buy_on": "gateio",
      "buy_price": 1.1873,
      "sell_on": "kucoin",
      "sell_price": 1.19,
      "profit_pct": 0.2274
    },
    {
      "symbol": "ZND/USDT",
      "buy_on": "kucoin",
      "buy_price": 0.2915,
      "sell_on": "gateio",
      "sell_price": 0.2921,
      "profit_pct": 0.2058
    }
  ]
}